{"namedChunkGroups":{"polyfill":{"name":"polyfill","assets":[{"name":"webpack-runtime-b3347e56984ed9b7fee4.js","size":4630},{"name":"polyfill-51f9f6ec785203067a38.js","size":84347}],"filteredAssets":0,"assetsSize":88977,"filteredAuxiliaryAssets":2,"auxiliaryAssetsSize":223770},"app":{"name":"app","assets":[{"name":"webpack-runtime-b3347e56984ed9b7fee4.js","size":4630},{"name":"framework-1f8db60c4f6292df0945.js","size":128904},{"name":"app-cd038e636ff1cd0bfa30.js","size":52334}],"filteredAssets":0,"assetsSize":185868,"filteredAuxiliaryAssets":3,"auxiliaryAssetsSize":553153},"component---src-pages-404-js":{"name":"component---src-pages-404-js","assets":[{"name":"styles.7f1c7375e3c167341354.css","size":7435},{"name":"commons-72e3d37f3d6dcd3a38b7.js","size":16485},{"name":"component---src-pages-404-js-a91ad3c55e203a56b258.js","size":1526}],"filteredAssets":0,"assetsSize":25446,"filteredAuxiliaryAssets":2,"auxiliaryAssetsSize":71121},"component---src-pages-about-js":{"name":"component---src-pages-about-js","assets":[{"name":"styles.7f1c7375e3c167341354.css","size":7435},{"name":"commons-72e3d37f3d6dcd3a38b7.js","size":16485},{"name":"component---src-pages-about-js-6098625e7a8283c9f30e.js","size":1684}],"filteredAssets":0,"assetsSize":25604,"filteredAuxiliaryAssets":2,"auxiliaryAssetsSize":71245},"component---src-pages-blog-js":{"name":"component---src-pages-blog-js","assets":[{"name":"styles.7f1c7375e3c167341354.css","size":7435},{"name":"commons-72e3d37f3d6dcd3a38b7.js","size":16485},{"name":"component---src-pages-blog-js-0593859f4e25fac00fd2.js","size":1849}],"filteredAssets":0,"assetsSize":25769,"filteredAuxiliaryAssets":2,"auxiliaryAssetsSize":72680},"component---src-pages-contact-js":{"name":"component---src-pages-contact-js","assets":[{"name":"styles.7f1c7375e3c167341354.css","size":7435},{"name":"commons-72e3d37f3d6dcd3a38b7.js","size":16485},{"name":"component---src-pages-contact-js-9daf51f9d4f8daa50c7e.js","size":1658}],"filteredAssets":0,"assetsSize":25578,"filteredAuxiliaryAssets":2,"auxiliaryAssetsSize":71220},"component---src-pages-index-js":{"name":"component---src-pages-index-js","assets":[{"name":"styles.7f1c7375e3c167341354.css","size":7435},{"name":"commons-72e3d37f3d6dcd3a38b7.js","size":16485},{"name":"component---src-pages-index-js-56ba1c5cedded9e3d663.js","size":2346}],"filteredAssets":0,"assetsSize":26266,"filteredAuxiliaryAssets":2,"auxiliaryAssetsSize":72858},"component---src-templates-blog-js":{"name":"component---src-templates-blog-js","assets":[{"name":"styles.7f1c7375e3c167341354.css","size":7435},{"name":"commons-72e3d37f3d6dcd3a38b7.js","size":16485},{"name":"component---src-templates-blog-js-b3e63a3420fdc8181926.js","size":19288}],"filteredAssets":0,"assetsSize":43208,"filteredAuxiliaryAssets":2,"auxiliaryAssetsSize":163450}},"assetsByChunkName":{"polyfill":["webpack-runtime-b3347e56984ed9b7fee4.js","polyfill-51f9f6ec785203067a38.js"],"app":["webpack-runtime-b3347e56984ed9b7fee4.js","framework-1f8db60c4f6292df0945.js","app-cd038e636ff1cd0bfa30.js"],"component---src-pages-404-js":["styles.7f1c7375e3c167341354.css","commons-72e3d37f3d6dcd3a38b7.js","component---src-pages-404-js-a91ad3c55e203a56b258.js"],"component---src-pages-about-js":["styles.7f1c7375e3c167341354.css","commons-72e3d37f3d6dcd3a38b7.js","component---src-pages-about-js-6098625e7a8283c9f30e.js"],"component---src-pages-blog-js":["styles.7f1c7375e3c167341354.css","commons-72e3d37f3d6dcd3a38b7.js","component---src-pages-blog-js-0593859f4e25fac00fd2.js"],"component---src-pages-contact-js":["styles.7f1c7375e3c167341354.css","commons-72e3d37f3d6dcd3a38b7.js","component---src-pages-contact-js-9daf51f9d4f8daa50c7e.js"],"component---src-pages-index-js":["styles.7f1c7375e3c167341354.css","commons-72e3d37f3d6dcd3a38b7.js","component---src-pages-index-js-56ba1c5cedded9e3d663.js"],"component---src-templates-blog-js":["styles.7f1c7375e3c167341354.css","commons-72e3d37f3d6dcd3a38b7.js","component---src-templates-blog-js-b3e63a3420fdc8181926.js"]},"childAssetsByChunkName":{}}